LICENSE
MANIFEST.in
Makefile
README.rst
changelog
requirements.txt
setup.py
mailreplay/__init__.py
mailreplay/debug.py
mailreplay/mailreplay.1.gz
mailreplay/parser.py
mailreplay/replay.py
mailreplay/run.py
mailreplay.egg-info/PKG-INFO
mailreplay.egg-info/SOURCES.txt
mailreplay.egg-info/dependency_links.txt
mailreplay.egg-info/entry_points.txt
mailreplay.egg-info/requires.txt
mailreplay.egg-info/top_level.txt
mailreplay.egg-info/zip-safe