Metadata-Version: 1.1
Name: mailreplay
Version: 0.2.0
Summary: Resend captured emails to localhost using SMTP
Home-page: UNKNOWN
Author: Henrik Levkowetz
Author-email: henrik@levkowetz.com
License: Simplified BSD
Keywords: SMTP email replay
Platform: UNKNOWN
Classifier: Development Status :: 4 - Beta
Classifier: Intended Audience :: Developers
Classifier: Topic :: Communications :: Email
Classifier: Topic :: Communications :: Email :: Mail Transport Agents
Classifier: License :: OSI Approved :: BSD License
Classifier: Programming Language :: Python :: 2
Classifier: Programming Language :: Python :: 2.7
